nudityradar
