Metadata-Version: 1.2
Name: nudityradar
Version: 0.2.5
Summary: Nudity detection with re-trained Tensorflow MobileNet Model http://nudity.canaydogan.net
Home-page: https://github.com/canaydogan/nudity
Author: Can Aydogan
Author-email: canaydogan89@gmail.com
License: MIT
Keywords: nude,nudity,detection,pornographic,inappropriate content
Platform: UNKNOWN
Classifier: Development Status :: 4 - Beta
Classifier: License :: OSI Approved :: MIT License
Classifier: Programming Language :: Python :: 3
Requires-Python: >=3
